{
    "MSEv": [
        {
            "MSEv": 1.405588152000372,
            "MSEv_sd": 0.06819204592637053
        }
    ],
    "MSEv_explicand": [
        {
            "id": 1,
            "MSEv": 0.7141043318086017
        },
        {
            "id": 2,
            "MSEv": 1.366292519443233
        },
        {
            "id": 3,
            "MSEv": 1.3648061810709626
        },
        {
            "id": 4,
            "MSEv": 1.3663021925635563
        },
        {
            "id": 5,
            "MSEv": 1.112898712727831
        },
        {
            "id": 6,
            "MSEv": 0.6059147959849348
        },
        {
            "id": 7,
            "MSEv": 1.1943244668786692
        },
        {
            "id": 8,
            "MSEv": 0.6460219641188448
        },
        {
            "id": 9,
            "MSEv": 0.8120439597737245
        },
        {
            "id": 10,
            "MSEv": 0.7198110872249959
        },
        {
            "id": 11,
            "MSEv": 0.5879711177271658
        },
        {
            "id": 12,
            "MSEv": 0.5646322694294265
        },
        {
            "id": 13,
            "MSEv": 0.5871997734564378
        },
        {
            "id": 14,
            "MSEv": 0.5379722018498264
        },
        {
            "id": 15,
            "MSEv": 0.35911666293229216
        },
        {
            "id": 16,
            "MSEv": 0.49667402168605984
        },
        {
            "id": 17,
            "MSEv": 0.698547089920006
        },
        {
            "id": 18,
            "MSEv": 0.6815117777140675
        },
        {
            "id": 19,
            "MSEv": 0.42293607198746586
        },
        {
            "id": 20,
            "MSEv": 0.8258204580836642
        },
        {
            "id": 21,
            "MSEv": 0.6734530593536171
        },
        {
            "id": 22,
            "MSEv": 1.0435042458421149
        },
        {
            "id": 23,
            "MSEv": 1.2137875239830571
        },
        {
            "id": 24,
            "MSEv": 0.8358331906327775
        },
        {
            "id": 25,
            "MSEv": 1.274178518495592
        },
        {
            "id": 26,
            "MSEv": 1.320827728939909
        },
        {
            "id": 27,
            "MSEv": 1.134271641741103
        },
        {
            "id": 28,
            "MSEv": 1.5092577357725134
        },
        {
            "id": 29,
            "MSEv": 0.6549673974437236
        },
        {
            "id": 30,
            "MSEv": 0.943280286800465
        },
        {
            "id": 31,
            "MSEv": 0.9403052912541398
        },
        {
            "id": 32,
            "MSEv": 1.3972059063995579
        },
        {
            "id": 33,
            "MSEv": 0.9369757555190803
        },
        {
            "id": 34,
            "MSEv": 1.5214497039166581
        },
        {
            "id": 35,
            "MSEv": 0.9132222465184021
        },
        {
            "id": 36,
            "MSEv": 1.17597506512167
        },
        {
            "id": 37,
            "MSEv": 0.9132222465184021
        },
        {
            "id": 38,
            "MSEv": 1.3752771139909339
        },
        {
            "id": 39,
            "MSEv": 1.2397743841850728
        },
        {
            "id": 40,
            "MSEv": 1.755743238388805
        },
        {
            "id": 41,
            "MSEv": 3.088004340385475
        },
        {
            "id": 42,
            "MSEv": 0.4558425982647965
        },
        {
            "id": 43,
            "MSEv": 3.088004340385475
        },
        {
            "id": 44,
            "MSEv": 1.3842815345232375
        },
        {
            "id": 45,
            "MSEv": 2.19328002376272
        },
        {
            "id": 46,
            "MSEv": 1.6273423360858867
        },
        {
            "id": 47,
            "MSEv": 1.2833793342262891
        },
        {
            "id": 48,
            "MSEv": 2.383898636175395
        },
        {
            "id": 49,
            "MSEv": 0.47584711686233644
        },
        {
            "id": 50,
            "MSEv": 1.1247310118794995
        },
        {
            "id": 51,
            "MSEv": 0.6512037230285335
        },
        {
            "id": 52,
            "MSEv": 1.1563112872424444
        },
        {
            "id": 53,
            "MSEv": 0.7636052088524251
        },
        {
            "id": 54,
            "MSEv": 1.064502349527927
        },
        {
            "id": 55,
            "MSEv": 0.717635782038206
        },
        {
            "id": 56,
            "MSEv": 1.0801262584157663
        },
        {
            "id": 57,
            "MSEv": 1.0664490438732068
        },
        {
            "id": 58,
            "MSEv": 0.695804331774273
        },
        {
            "id": 59,
            "MSEv": 2.1341199091468446
        },
        {
            "id": 60,
            "MSEv": 2.0575992337165494
        },
        {
            "id": 61,
            "MSEv": 2.6232921426259326
        },
        {
            "id": 62,
            "MSEv": 1.6820734959073225
        },
        {
            "id": 63,
            "MSEv": 0.7040001142155368
        },
        {
            "id": 64,
            "MSEv": 1.5476539167138184
        },
        {
            "id": 65,
            "MSEv": 2.087798456177198
        },
        {
            "id": 66,
            "MSEv": 0.8790649013201487
        },
        {
            "id": 67,
            "MSEv": 1.8721325466669718
        },
        {
            "id": 68,
            "MSEv": 1.553550927029831
        },
        {
            "id": 69,
            "MSEv": 1.5556094732140586
        },
        {
            "id": 70,
            "MSEv": 1.7913733037839383
        },
        {
            "id": 71,
            "MSEv": 3.68909186564842
        },
        {
            "id": 72,
            "MSEv": 0.9473550090383674
        },
        {
            "id": 73,
            "MSEv": 1.1243353735805008
        },
        {
            "id": 74,
            "MSEv": 0.7860151472193595
        },
        {
            "id": 75,
            "MSEv": 1.0995618158114415
        },
        {
            "id": 76,
            "MSEv": 1.83846143429493
        },
        {
            "id": 77,
            "MSEv": 1.4759073871037027
        },
        {
            "id": 78,
            "MSEv": 2.4071748455494495
        },
        {
            "id": 79,
            "MSEv": 1.7485131677567476
        },
        {
            "id": 80,
            "MSEv": 2.083228797879709
        },
        {
            "id": 81,
            "MSEv": 0.6353552828798933
        },
        {
            "id": 82,
            "MSEv": 2.4207171047988867
        },
        {
            "id": 83,
            "MSEv": 1.5924805537786884
        },
        {
            "id": 84,
            "MSEv": 2.9672114363757713
        },
        {
            "id": 85,
            "MSEv": 2.5754551535019985
        },
        {
            "id": 86,
            "MSEv": 1.2026636240895003
        },
        {
            "id": 87,
            "MSEv": 1.5753694774188778
        },
        {
            "id": 88,
            "MSEv": 1.2356263932006943
        },
        {
            "id": 89,
            "MSEv": 2.285661864608608
        },
        {
            "id": 90,
            "MSEv": 1.4380985558789272
        },
        {
            "id": 91,
            "MSEv": 2.007384641548703
        },
        {
            "id": 92,
            "MSEv": 1.6905787198192037
        },
        {
            "id": 93,
            "MSEv": 1.9184281133286198
        },
        {
            "id": 94,
            "MSEv": 1.4782981519121707
        },
        {
            "id": 95,
            "MSEv": 1.7039802263095871
        },
        {
            "id": 96,
            "MSEv": 1.8618822371256822
        },
        {
            "id": 97,
            "MSEv": 1.2996437357437902
        },
        {
            "id": 98,
            "MSEv": 1.2175842614340837
        },
        {
            "id": 99,
            "MSEv": 1.632922180297333
        },
        {
            "id": 100,
            "MSEv": 3.2115064684131447
        },
        {
            "id": 101,
            "MSEv": 1.6524503913239623
        },
        {
            "id": 102,
            "MSEv": 2.807688996599623
        },
        {
            "id": 103,
            "MSEv": 1.75476896904836
        },
        {
            "id": 104,
            "MSEv": 1.699361956522837
        },
        {
            "id": 105,
            "MSEv": 1.7048777730947358
        },
        {
            "id": 106,
            "MSEv": 2.9967713840816983
        }
    ]
}